django_seeding/__init__.py
django_seeding/admin.py
django_seeding/apps.py
django_seeding/cache_methods.py
django_seeding/casting_methods.py
django_seeding/hashable_dict.py
django_seeding/models.py
django_seeding/seeder_registry.py
django_seeding/seeders.py
django_seeding/apis/__init__.py
django_seeding/apis/serializers.py
django_seeding/apis/views.py
django_seeding/management/__init__.py
django_seeding/management/commands/__init__.py
django_seeding/management/commands/runserver.py
django_seeding/management/commands/seed.py
django_seeding/migrations/0001_initial.py
django_seeding/migrations/0002_appliedseeder_created_at_appliedseeder_updated_at.py
django_seeding/migrations/__init__.py
django_seeding-1.3.6.dist-info/LICENSE
django_seeding-1.3.6.dist-info/METADATA
django_seeding-1.3.6.dist-info/WHEEL
django_seeding-1.3.6.dist-info/top_level.txt
django_seeding-1.3.6.dist-info/RECORD
