Metadata-Version: 2.1
Name: django-seeding
Version: 1.3.6
Summary: Simple Django Package that helps developer to seed data from files and codes into the database automatically
Author-email: Suliman Awad <sulimanawadstudy@gmail.com>
Project-URL: Source, https://github.com/suliman-99/django-seeding
Project-URL: Contributors, https://github.com/suliman-99/django-seeding/graphs/contributors
Project-URL: License, https://github.com/suliman-99/django-seeding/blob/main/LICENSE
Project-URL: Issues, https://github.com/suliman-99/django-seeding/issues
Classifier: Programming Language :: Python
Classifier: Framework :: Django
License-File: LICENSE
